simple_mri/__init__.py
simple_mri/py.typed
simple_mri/simple_mri.py
simple_mri-0.1.6.dist-info/LICENSE
simple_mri-0.1.6.dist-info/METADATA
simple_mri-0.1.6.dist-info/WHEEL
simple_mri-0.1.6.dist-info/top_level.txt
simple_mri-0.1.6.dist-info/RECORD
