Metadata-Version: 2.2
Name: simple-mri
Version: 0.1.6
Summary: Simple MRI-utility wrapper around nibabel.
Author-email: Jørgen Riseth <jnriseth@gmail.com>
Requires-Python: >=3.9
License-File: LICENSE
Requires-Dist: nibabel>=5.0.0
Requires-Dist: numpy>=1.0.0
